AUTHORS.rst
CONTRIBUTING.rst
HISTORY.rst
LICENSE
MANIFEST.in
README.rst
setup.cfg
setup.py
punch/__init__.py
punch/action_register.py
punch/cli.py
punch/config.py
punch/file_configuration.py
punch/file_updater.py
punch/helpers.py
punch/replacer.py
punch/vcs_configuration.py
punch/version.py
punch/version_part.py
punch.py.egg-info/PKG-INFO
punch.py.egg-info/SOURCES.txt
punch.py.egg-info/dependency_links.txt
punch.py.egg-info/entry_points.txt
punch.py.egg-info/not-zip-safe
punch.py.egg-info/requires.txt
punch.py.egg-info/top_level.txt
punch/actions/__init__.py
punch/actions/conditional_reset.py
punch/actions/increase_part.py
punch/actions/set_part.py
punch/vcs_repositories/__init__.py
punch/vcs_repositories/exceptions.py
punch/vcs_repositories/git_flow_repo.py
punch/vcs_repositories/git_repo.py
punch/vcs_repositories/hg_repo.py
punch/vcs_repositories/novcs_repo.py
punch/vcs_repositories/vcs_repo.py
punch/vcs_use_cases/__init__.py
punch/vcs_use_cases/release.py
punch/vcs_use_cases/tag.py
punch/vcs_use_cases/use_case.py
punch/vcs_use_cases/vcs_finish_release.py
punch/vcs_use_cases/vcs_start_release.py
tests/__init__.py
tests/conftest.py
tests/test_action_register.py
tests/test_config.py
tests/test_file_configuration.py
tests/test_file_updater.py
tests/test_helpers.py
tests/test_replacer.py
tests/test_vcs_configuration.py
tests/test_version.py
tests/test_version_part.py
tests/actions/test_conditional_reset.py
tests/actions/test_increase_part.py
tests/actions/test_set_part.py
tests/script/.coverage
tests/script/__init__.py
tests/script/conftest.py
tests/script/test_action_conditional_reset_increment.py
tests/script/test_action_conditional_reset_reset.py
tests/script/test_action_increase_part.py
tests/script/test_action_set_part.py
tests/script/test_calver.py
tests/script/test_complex_serializers.py
tests/script/test_date.py
tests/script/test_dedicated_serializer.py
tests/script/test_file_addition.py
tests/script/test_full_date_string.py
tests/script/test_init.py
tests/script/test_misconfigured_action.py
tests/script/test_named_serializers.py
tests/script/test_plain_semver.py
tests/script/test_punch.py
tests/script/test_quotes.py
tests/script/test_release_notes.py
