Metadata-Version: 1.1
Name: punch.py
Version: 2.0.0
Summary: Update your version while having a drink
Home-page: https://github.com/lgiordani/punch
Author: Leonardo Giordani
Author-email: giordani.leonardo@gmail.com
License: MIT
Keywords: version,management
Platform: UNKNOWN
Classifier: Development Status :: 5 - Production/Stable
Classifier: Intended Audience :: Developers
Classifier: License :: OSI Approved :: MIT License
Classifier: Natural Language :: English
Classifier: Programming Language :: Python :: 2
Classifier: Programming Language :: Python :: 2.7
Classifier: Programming Language :: Python :: 3
Classifier: Programming Language :: Python :: 3.4
Classifier: Programming Language :: Python :: 3.5
